SegByKmeans/Kmeans.py
SegByKmeans/Seg.py
SegByKmeans/__init__.py
SegbyKmeans-1.0.dist-info/LICENSE
SegbyKmeans-1.0.dist-info/METADATA
SegbyKmeans-1.0.dist-info/WHEEL
SegbyKmeans-1.0.dist-info/top_level.txt
SegbyKmeans-1.0.dist-info/RECORD
