Metadata-Version: 2.1
Name: SegbyKmeans
Version: 1.0
Summary: This is my first packages
Author: YuKun Zhou
Author-email: Yu-Kun-Zhou@outlook.com
Classifier: Programming Language :: Python :: 3
Classifier: License :: OSI Approved :: MIT License
Classifier: Operating System :: OS Independent
Requires-Python: >=3
License-File: LICENSE
Requires-Dist: opencv-python
